oc_image_segmentation/__init__.py
oc_image_segmentation/__main__.py
oc_image_segmentation/cli.py
oc_image_segmentation/config.py
oc_image_segmentation/utils.py
oc_image_segmentation/cli/__init__.py
oc_image_segmentation/cli/__main__.py
oc_image_segmentation/cli/commands/__init__.py
oc_image_segmentation/cli/commands/dataset.py
oc_image_segmentation/cli/commands/model.py
oc_image_segmentation/cli/commands/segment.py
oc_image_segmentation/cli/parsers/__init__.py
oc_image_segmentation/cli/parsers/argument_parser.py
oc_image_segmentation/datasets/__init__.py
oc_image_segmentation/datasets/cityscapes.py
oc_image_segmentation/datasets/cityscapes_labels.py
oc_image_segmentation/datasets/convert_labels.py
oc_image_segmentation/datasets/factory.py
oc_image_segmentation/datasets/preprocessing.py
oc_image_segmentation/datasets/utils.py
oc_image_segmentation/models/__init__.py
oc_image_segmentation/models/base_model.py
oc_image_segmentation/models/callbacks.py
oc_image_segmentation/models/deeplabv3plus.py
oc_image_segmentation/models/evaluation.py
oc_image_segmentation/models/factory.py
oc_image_segmentation/models/layers.py
oc_image_segmentation/models/losses.py
oc_image_segmentation/models/metrics.py
oc_image_segmentation/models/training.py
oc_image_segmentation/models/unet.py
oc_image_segmentation-0.2.0.dist-info/licenses/LICENSE
oc_image_segmentation-0.2.0.dist-info/METADATA
oc_image_segmentation-0.2.0.dist-info/WHEEL
oc_image_segmentation-0.2.0.dist-info/entry_points.txt
oc_image_segmentation-0.2.0.dist-info/top_level.txt
oc_image_segmentation-0.2.0.dist-info/RECORD
