Metadata-Version: 2.4
Name: oc-image-segmentation
Version: 0.2.0
Summary: A Python library for image segmentation using OpenCV and deep learning models.
Author-email: Florent Pigout <florent@toopy.org>
Classifier: Development Status :: 3 - Alpha
Classifier: Intended Audience :: Developers
Classifier: License :: OSI Approved :: MIT License
Classifier: Programming Language :: Python :: 3
Classifier: Programming Language :: Python :: 3.11
Classifier: Topic :: Scientific/Engineering :: Artificial Intelligence
Classifier: Topic :: Scientific/Engineering :: Image Recognition
Classifier: Topic :: Scientific/Engineering :: Image Processing
Requires-Python: >=3.11
License-File: LICENSE
Requires-Dist: albumentations
Requires-Dist: cityscapesscripts
Requires-Dist: dynaconf
Requires-Dist: keras==3.8.0
Requires-Dist: numpy
Requires-Dist: pillow
Requires-Dist: pyyaml
Requires-Dist: scikit-learn
Requires-Dist: tensorflow==2.18.0
Provides-Extra: extra
Requires-Dist: matplotlib; extra == "extra"
Requires-Dist: pandas; extra == "extra"
Provides-Extra: lint
Requires-Dist: pre-commit; extra == "lint"
Requires-Dist: yamllint; extra == "lint"
Provides-Extra: test
Requires-Dist: pytest-cov; extra == "test"
Requires-Dist: pytest; extra == "test"
Dynamic: license-file
